OpenTrepWrapper/OpenTrepWrapper.py
OpenTrepWrapper/__init__.py
OpenTrepWrapper/cli.py
OpenTrepWrapper/utilities.py
OpenTrepWrapper-0.7.7.post3.dist-info/METADATA
OpenTrepWrapper-0.7.7.post3.dist-info/WHEEL
OpenTrepWrapper-0.7.7.post3.dist-info/entry_points.txt
OpenTrepWrapper-0.7.7.post3.dist-info/top_level.txt
OpenTrepWrapper-0.7.7.post3.dist-info/RECORD
