Metadata-Version: 2.1
Name: OpenTrepWrapper
Version: 0.7.7.post3
Summary: A Python wrapper module for OpenTrep
Home-page: https://github.com/trep/wrapper
Author: Denis Arnaud
Author-email: Denis Arnaud <denis.arnaud_fedora@m4x.org>
Project-URL: documentation, https://opentrep.readthedocs.io/en/latest/
Project-URL: changelog, https://opentrep.readthedocs.io/en/latest/opentrep.html
Keywords: data,trep,request,parser,travel,transport,search,wrapper,optd,opentraveldata,opentrep
Classifier: Development Status :: 5 - Production/Stable
Classifier: Intended Audience :: Developers
Classifier: License :: OSI Approved :: MIT License
Classifier: Operating System :: POSIX
Classifier: Programming Language :: Python :: 3
Classifier: Topic :: Utilities
Requires-Python: >=2.7, !=3.0.*, !=3.1.*, !=3.2.*, !=3.3.*, !=3.4.*
